{
 "lcc": {
  "AG": 1,
  "B1-5802": 1,
  "BD": 1,
  "GN496": 1,
  "HM623": 1,
  "HN18.3": 1,
  "LC8-6691": 1,
  "N72.F53": 1,
  "P85.E25": 1,
  "P92.5.E26": 1,
  "PQ": 4,
  "PQ1979.A653": 1,
  "PQ4253.A9.S783 2006eb": 1,
  "PQ4809.A45 -- .C358 2016eb": 1,
  "PQ4865.C6": 6,
  "TR79": 1
 },
 "ddc": {
  "000": 2,
  "001": 1,
  "111.85": 1,
  "121": 1,
  "300": 1,
  "302": 1,
  "305.8": 1,
  "306": 4,
  "370.1": 1,
  "700": 3,
  "704.94911185": 1,
  "740": 1,
  "770.94509/04": 1,
  "791": 1,
  "800": 3,
  "830": 2,
  "830 B": 2,
  "840": 1,
  "850": 5,
  "850 B": 1,
  "853": 6,
  "853.01080913999999": 1,
  "853.91399999999999": 1,
  "853.914": 2,
  "853/.914": 2
 },
 "bisacsh": {},
 "BISAC": {
  "ART 043000": 1,
  "ART015000": 1,
  "EDU040000": 1,
  "HIS020000": 1,
  "LAN009000": 1,
  "LIT 004200": 1,
  "LIT000000": 1,
  "LIT004200": 1,
  "SOC 026000": 1,
  "SOC002010": 1,
  "SOC022000": 1,
  "SOC026000": 1,
  "SOC052000": 1
 },
 "bkl": {
  "08.41": 1,
  "08.99": 1,
  "11.40": 1,
  "15.08": 1,
  "17.08": 2,
  "17.81": 2,
  "17.84": 1,
  "17.93": 1,
  "17.95": 1,
  "17.97": 5,
  "18.00": 2,
  "18.06": 1,
  "18.27": 7,
  "18.37": 1,
  "20.06": 3,
  "21.39": 1,
  "21.80": 1
 },
 "rvk": {
  "AP 88890": 2,
  "AP 88930": 1,
  "CC 6700": 1,
  "CC 6900": 1,
  "EC 1840": 1,
  "EC 1980": 1,
  "EC 3000": 1,
  "EC 5410": 1,
  "EC 7120": 1,
  "ER 730": 1,
  "IG 2255": 1,
  "IV 25480": 9,
  "IV 25481": 3,
  "LC 90000": 1,
  "LH 61040": 2,
  "LH 65020": 1,
  "LH 79540": 1,
  "MS 1290": 1
 }
}